openapy/__init__.py
openapy/args.py
openapy/commands/example.py
openapy/commands/generate.py
openapy/commands/version.py
openapy/config.py
openapy/diff.py
openapy/examples/api.mustache
openapy/examples/docker.sh
openapy/examples/template.py.txt
openapy/io.py
openapy/main.py
openapy/parser.py
openapy/render.py
openapy/template.py
openapy-0.3.1.dist-info/entry_points.txt
openapy-0.3.1.dist-info/LICENSE
openapy-0.3.1.dist-info/WHEEL
openapy-0.3.1.dist-info/METADATA
openapy-0.3.1.dist-info/RECORD
