Metadata-Version: 2.1
Name: openapy
Version: 0.3.1
Summary: 
Home-page: https://github.com/edge-minato/openapy
License: MIT
Keywords: developent
Author: edge-minato
Author-email: edge.minato@gmail.com
Requires-Python: >=3.9,<4.0
Classifier: Development Status :: 1 - Planning
Classifier: Environment :: Console
Classifier: Intended Audience :: Developers
Classifier: License :: OSI Approved :: MIT License
Classifier: Operating System :: Unix
Classifier: Programming Language :: Python :: 3
Classifier: Programming Language :: Python :: 3.10
Classifier: Programming Language :: Python :: 3.9
Classifier: Topic :: Software Development :: Libraries :: Python Modules
Requires-Dist: single-source (>=0.2,<0.4)
Project-URL: Repository, https://github.com/edge-minato/openapy
